taskwarrior/__init__.py
taskwarrior/client.py
taskwarrior/exceptions.py
taskwarrior/task.py
taskwarrior/types.py
taskwarrior/utils.py
taskwarrior/tests/__init__.py
taskwarrior/tests/test_client.py
taskwarrior/tests/fixtures/backlog.data
taskwarrior/tests/fixtures/completed.data
taskwarrior/tests/fixtures/pending.data
taskwarrior/tests/fixtures/taskrc
taskwarrior/tests/fixtures/undo.data
taskwarrior-0.1.2.dist-info/LICENSE
taskwarrior-0.1.2.dist-info/METADATA
taskwarrior-0.1.2.dist-info/WHEEL
taskwarrior-0.1.2.dist-info/top_level.txt
taskwarrior-0.1.2.dist-info/RECORD
