Metadata-Version: 2.1
Name: taskwarrior
Version: 0.1.2
Summary: Interact with your local taskwarrior task list from Python.
Home-page: https://github.com/coddingtonbear/taskwarrior
Author: Adam Coddington
Author-email: me@adamcoddington.net
License: MIT
Project-URL: Changelog, https://github.com/coddingtonbear/taskwarrior/blob/master/CHANGELOG.md
Project-URL: Issue Tracker, https://github.com/coddingtonbear/taskwarrior/issues
Platform: UNKNOWN
Classifier: Development Status :: 5 - Production/Stable
Classifier: Intended Audience :: Developers
Classifier: License :: OSI Approved :: MIT License
Classifier: Operating System :: Unix
Classifier: Operating System :: POSIX
Classifier: Operating System :: Microsoft :: Windows
Classifier: Programming Language :: Python
Classifier: Programming Language :: Python :: 3
Classifier: Programming Language :: Python :: 3 :: Only
Classifier: Programming Language :: Python :: 3.7
Classifier: Programming Language :: Python :: 3.8
Classifier: Programming Language :: Python :: 3.9
Classifier: Programming Language :: Python :: Implementation :: CPython
Classifier: Programming Language :: Python :: Implementation :: PyPy
Classifier: Topic :: Utilities
Requires-Python: >=3.6
License-File: LICENSE
Requires-Dist: pydantic (<2.0.0,>=1.8.2)
Requires-Dist: python-dateutil (<3.0.0,>=2.8.2)
Requires-Dist: pytz
Requires-Dist: typing-extensions
